README.md
setup.py
youtube_comment_scraper_python/__init__.py
youtube_comment_scraper_python.egg-info/PKG-INFO
youtube_comment_scraper_python.egg-info/SOURCES.txt
youtube_comment_scraper_python.egg-info/dependency_links.txt
youtube_comment_scraper_python.egg-info/requires.txt
youtube_comment_scraper_python.egg-info/top_level.txt